Metadata-Version: 2.1
Name: projeto-02
Version: 0.0.1
Summary: Projeto 2 DIO / Unimed
Home-page: https://github.com/igorjvmata/Projeto_02
Author: Igor Mata
Author-email: igor@mata.com.br
License: UNKNOWN
Platform: UNKNOWN
